split_code/__init__.py
split_code/max_length_split.py
sequence_cut-0.0.2.dist-info/LICENSE
sequence_cut-0.0.2.dist-info/METADATA
sequence_cut-0.0.2.dist-info/WHEEL
sequence_cut-0.0.2.dist-info/top_level.txt
sequence_cut-0.0.2.dist-info/RECORD
