Metadata-Version: 2.1
Name: sequence-cut
Version: 0.0.2
Summary: Cut a sequence to some sub-sequences by specifying a maxinum sub-sequence length.
Home-page: https://github.com/BlueSkyBubble/script
Author: BlueSkyBubble
Author-email: yajie.wagn@gmail.com
License: UNKNOWN
Platform: UNKNOWN
Classifier: Programming Language :: Python :: 3
Classifier: License :: OSI Approved :: MIT License
Classifier: Operating System :: OS Independent
